[
  {
    "inputs": [
      {
        "internalType": "uint256",
        "name": "_subscriptionStartTime",
        "type": "uint256"
      },
      {
        "internalType": "uint256",
        "name": "_subscriptionEndTime",
        "type": "uint256"
      },
      {
        "internalType": "uint256",
        "name": "_paymentDueTime",
        "type": "uint256"
      },
      {
        "internalType": "uint256",
        "name": "_allocationAnnouncementTime",
        "type": "uint256"
      }
    ],
    "stateMutability": "nonpayable",
    "type": "constructor"
  },
  {
    "inputs": [
      {
        "internalType": "address",
        "name": "owner",
        "type": "address"
      }
    ],
    "name": "OwnableInvalidOwner",
    "type": "error"
  },
  {
    "inputs": [
      {
        "internalType": "address",
        "name": "account",
        "type": "address"
      }
    ],
    "name": "OwnableUnauthorizedAccount",
    "type": "error"
  },
  {
    "inputs": [],
    "name": "ReentrancyGuardReentrantCall",
    "type": "error"
  },
  {
    "anonymous": false,
    "inputs": [
      {
        "indexed": true,
        "internalType": "address",
        "name": "investor",
        "type": "address"
      },
      {
        "indexed": false,
        "internalType": "uint256",
        "name": "amount",
        "type": "uint256"
      }
    ],
    "name": "Allocation",
    "type": "event"
  },
  {
    "anonymous": false,
    "inputs": [
      {
        "indexed": true,
        "internalType": "address",
        "name": "investor",
        "type": "address"
      },
      {
        "indexed": false,
        "internalType": "uint256",
        "name": "amount",
        "type": "uint256"
      }
    ],
    "name": "DividendClaimed",
    "type": "event"
  },
  {
    "anonymous": false,
    "inputs": [
      {
        "indexed": false,
        "internalType": "uint256",
        "name": "quarter",
        "type": "uint256"
      },
      {
        "indexed": false,
        "internalType": "uint256",
        "name": "totalAmount",
        "type": "uint256"
      }
    ],
    "name": "DividendDistributed",
    "type": "event"
  },
  {
    "anonymous": false,
    "inputs": [
      {
        "indexed": true,
        "internalType": "address",
        "name": "oldOperator",
        "type": "address"
      },
      {
        "indexed": true,
        "internalType": "address",
        "name": "newOperator",
        "type": "address"
      }
    ],
    "name": "EmergencyOperatorChanged",
    "type": "event"
  },
  {
    "anonymous": false,
    "inputs": [
      {
        "indexed": true,
        "internalType": "address",
        "name": "previousOwner",
        "type": "address"
      },
      {
        "indexed": true,
        "internalType": "address",
        "name": "newOwner",
        "type": "address"
      }
    ],
    "name": "OwnershipTransferred",
    "type": "event"
  },
  {
    "anonymous": false,
    "inputs": [
      {
        "indexed": true,
        "internalType": "address",
        "name": "investor",
        "type": "address"
      },
      {
        "indexed": false,
        "internalType": "uint256",
        "name": "amount",
        "type": "uint256"
      }
    ],
    "name": "Payment",
    "type": "event"
  },
  {
    "anonymous": false,
    "inputs": [
      {
        "indexed": false,
        "internalType": "uint256",
        "name": "proposalId",
        "type": "uint256"
      },
      {
        "indexed": false,
        "internalType": "string",
        "name": "description",
        "type": "string"
      }
    ],
    "name": "ProposalCreated",
    "type": "event"
  },
  {
    "anonymous": false,
    "inputs": [
      {
        "indexed": false,
        "internalType": "uint256",
        "name": "proposalId",
        "type": "uint256"
      }
    ],
    "name": "ProposalExecuted",
    "type": "event"
  },
  {
    "anonymous": false,
    "inputs": [
      {
        "indexed": true,
        "internalType": "address",
        "name": "investor",
        "type": "address"
      },
      {
        "indexed": false,
        "internalType": "uint256",
        "name": "amount",
        "type": "uint256"
      }
    ],
    "name": "Subscription",
    "type": "event"
  },
  {
    "anonymous": false,
    "inputs": [
      {
        "indexed": false,
        "internalType": "uint256",
        "name": "proposalId",
        "type": "uint256"
      },
      {
        "indexed": true,
        "internalType": "address",
        "name": "voter",
        "type": "address"
      },
      {
        "indexed": false,
        "internalType": "bool",
        "name": "support",
        "type": "bool"
      }
    ],
    "name": "Voted",
    "type": "event"
  },
  {
    "inputs": [],
    "name": "FEE_DENOMINATOR",
    "outputs": [
      {
        "internalType": "uint256",
        "name": "",
        "type": "uint256"
      }
    ],
    "stateMutability": "view",
    "type": "function"
  },
  {
    "inputs": [],
    "name": "MAX_DESCRIPTION_LENGTH",
    "outputs": [
      {
        "internalType": "uint256",
        "name": "",
        "type": "uint256"
      }
    ],
    "stateMutability": "view",
    "type": "function"
  },
  {
    "inputs": [],
    "name": "MAX_PROPOSAL_DURATION",
    "outputs": [
      {
        "internalType": "uint256",
        "name": "",
        "type": "uint256"
      }
    ],
    "stateMutability": "view",
    "type": "function"
  },
  {
    "inputs": [],
    "name": "MAX_SUBSCRIPTION_PER_PERSON",
    "outputs": [
      {
        "internalType": "uint256",
        "name": "",
        "type": "uint256"
      }
    ],
    "stateMutability": "view",
    "type": "function"
  },
  {
    "inputs": [],
    "name": "MIN_PROPOSAL_DURATION",
    "outputs": [
      {
        "internalType": "uint256",
        "name": "",
        "type": "uint256"
      }
    ],
    "stateMutability": "view",
    "type": "function"
  },
  {
    "inputs": [],
    "name": "MIN_SUBSCRIPTION",
    "outputs": [
      {
        "internalType": "uint256",
        "name": "",
        "type": "uint256"
      }
    ],
    "stateMutability": "view",
    "type": "function"
  },
  {
    "inputs": [],
    "name": "PROJECT_NAME",
    "outputs": [
      {
        "internalType": "string",
        "name": "",
        "type": "string"
      }
    ],
    "stateMutability": "view",
    "type": "function"
  },
  {
    "inputs": [],
    "name": "PROJECT_SYMBOL",
    "outputs": [
      {
        "internalType": "string",
        "name": "",
        "type": "string"
      }
    ],
    "stateMutability": "view",
    "type": "function"
  },
  {
    "inputs": [],
    "name": "TOKEN_PRICE",
    "outputs": [
      {
        "internalType": "uint256",
        "name": "",
        "type": "uint256"
      }
    ],
    "stateMutability": "view",
    "type": "function"
  },
  {
    "inputs": [],
    "name": "TOTAL_SUPPLY",
    "outputs": [
      {
        "internalType": "uint256",
        "name": "",
        "type": "uint256"
      }
    ],
    "stateMutability": "view",
    "type": "function"
  },
  {
    "inputs": [
      {
        "internalType": "address",
        "name": "investor",
        "type": "address"
      },
      {
        "internalType": "uint256",
        "name": "amount",
        "type": "uint256"
      }
    ],
    "name": "allocateTokens",
    "outputs": [],
    "stateMutability": "nonpayable",
    "type": "function"
  },
  {
    "inputs": [],
    "name": "allocationAnnouncementTime",
    "outputs": [
      {
        "internalType": "uint256",
        "name": "",
        "type": "uint256"
      }
    ],
    "stateMutability": "view",
    "type": "function"
  },
  {
    "inputs": [
      {
        "internalType": "uint256",
        "name": "dividendId",
        "type": "uint256"
      }
    ],
    "name": "claimDividend",
    "outputs": [],
    "stateMutability": "nonpayable",
    "type": "function"
  },
  {
    "inputs": [
      {
        "internalType": "string",
        "name": "description",
        "type": "string"
      },
      {
        "internalType": "uint256",
        "name": "duration",
        "type": "uint256"
      }
    ],
    "name": "createProposal",
    "outputs": [],
    "stateMutability": "nonpayable",
    "type": "function"
  },
  {
    "inputs": [],
    "name": "daoFeeRate",
    "outputs": [
      {
        "internalType": "uint256",
        "name": "",
        "type": "uint256"
      }
    ],
    "stateMutability": "view",
    "type": "function"
  },
  {
    "inputs": [],
    "name": "dividendCounter",
    "outputs": [
      {
        "internalType": "uint256",
        "name": "",
        "type": "uint256"
      }
    ],
    "stateMutability": "view",
    "type": "function"
  },
  {
    "inputs": [
      {
        "internalType": "uint256",
        "name": "",
        "type": "uint256"
      }
    ],
    "name": "dividends",
    "outputs": [
      {
        "internalType": "uint256",
        "name": "quarter",
        "type": "uint256"
      },
      {
        "internalType": "uint256",
        "name": "totalAmount",
        "type": "uint256"
      },
      {
        "internalType": "uint256",
        "name": "distributedAmount",
        "type": "uint256"
      },
      {
        "internalType": "uint256",
        "name": "timestamp",
        "type": "uint256"
      },
      {
        "internalType": "bool",
        "name": "isDistributed",
        "type": "bool"
      }
    ],
    "stateMutability": "view",
    "type": "function"
  },
  {
    "inputs": [],
    "name": "emergencyOperator",
    "outputs": [
      {
        "internalType": "address",
        "name": "",
        "type": "address"
      }
    ],
    "stateMutability": "view",
    "type": "function"
  },
  {
    "inputs": [],
    "name": "emergencyPause",
    "outputs": [],
    "stateMutability": "nonpayable",
    "type": "function"
  },
  {
    "inputs": [],
    "name": "emergencyPaused",
    "outputs": [
      {
        "internalType": "bool",
        "name": "",
        "type": "bool"
      }
    ],
    "stateMutability": "view",
    "type": "function"
  },
  {
    "inputs": [],
    "name": "emergencyUnpause",
    "outputs": [],
    "stateMutability": "nonpayable",
    "type": "function"
  },
  {
    "inputs": [
      {
        "internalType": "uint256",
        "name": "proposalId",
        "type": "uint256"
      }
    ],
    "name": "executeProposal",
    "outputs": [],
    "stateMutability": "nonpayable",
    "type": "function"
  },
  {
    "inputs": [],
    "name": "getContractBalance",
    "outputs": [
      {
        "internalType": "uint256",
        "name": "",
        "type": "uint256"
      }
    ],
    "stateMutability": "view",
    "type": "function"
  },
  {
    "inputs": [
      {
        "internalType": "uint256",
        "name": "dividendId",
        "type": "uint256"
      }
    ],
    "name": "getDividendInfo",
    "outputs": [
      {
        "internalType": "uint256",
        "name": "quarter",
        "type": "uint256"
      },
      {
        "internalType": "uint256",
        "name": "totalAmount",
        "type": "uint256"
      },
      {
        "internalType": "uint256",
        "name": "distributedAmount",
        "type": "uint256"
      },
      {
        "internalType": "uint256",
        "name": "timestamp",
        "type": "uint256"
      },
      {
        "internalType": "bool",
        "name": "isDistributed",
        "type": "bool"
      }
    ],
    "stateMutability": "view",
    "type": "function"
  },
  {
    "inputs": [
      {
        "internalType": "address",
        "name": "investor",
        "type": "address"
      }
    ],
    "name": "getInvestorInfo",
    "outputs": [
      {
        "internalType": "uint256",
        "name": "subscribedAmount",
        "type": "uint256"
      },
      {
        "internalType": "uint256",
        "name": "allocatedAmount",
        "type": "uint256"
      },
      {
        "internalType": "bool",
        "name": "hasPaid",
        "type": "bool"
      },
      {
        "internalType": "bool",
        "name": "isVerified",
        "type": "bool"
      },
      {
        "internalType": "uint256",
        "name": "votingPower",
        "type": "uint256"
      },
      {
        "internalType": "uint256",
        "name": "lastDividendClaim",
        "type": "uint256"
      }
    ],
    "stateMutability": "view",
    "type": "function"
  },
  {
    "inputs": [
      {
        "internalType": "uint256",
        "name": "proposalId",
        "type": "uint256"
      }
    ],
    "name": "getProposalInfo",
    "outputs": [
      {
        "internalType": "string",
        "name": "description",
        "type": "string"
      },
      {
        "internalType": "uint256",
        "name": "forVotes",
        "type": "uint256"
      },
      {
        "internalType": "uint256",
        "name": "againstVotes",
        "type": "uint256"
      },
      {
        "internalType": "uint256",
        "name": "startTime",
        "type": "uint256"
      },
      {
        "internalType": "uint256",
        "name": "endTime",
        "type": "uint256"
      },
      {
        "internalType": "bool",
        "name": "executed",
        "type": "bool"
      },
      {
        "internalType": "bool",
        "name": "canceled",
        "type": "bool"
      }
    ],
    "stateMutability": "view",
    "type": "function"
  },
  {
    "inputs": [
      {
        "internalType": "address",
        "name": "",
        "type": "address"
      },
      {
        "internalType": "uint256",
        "name": "",
        "type": "uint256"
      }
    ],
    "name": "hasVoted",
    "outputs": [
      {
        "internalType": "bool",
        "name": "",
        "type": "bool"
      }
    ],
    "stateMutability": "view",
    "type": "function"
  },
  {
    "inputs": [
      {
        "internalType": "address",
        "name": "",
        "type": "address"
      }
    ],
    "name": "investors",
    "outputs": [
      {
        "internalType": "uint256",
        "name": "subscribedAmount",
        "type": "uint256"
      },
      {
        "internalType": "uint256",
        "name": "allocatedAmount",
        "type": "uint256"
      },
      {
        "internalType": "bool",
        "name": "hasPaid",
        "type": "bool"
      },
      {
        "internalType": "bool",
        "name": "isVerified",
        "type": "bool"
      },
      {
        "internalType": "uint256",
        "name": "votingPower",
        "type": "uint256"
      },
      {
        "internalType": "uint256",
        "name": "lastDividendClaim",
        "type": "uint256"
      }
    ],
    "stateMutability": "view",
    "type": "function"
  },
  {
    "inputs": [],
    "name": "owner",
    "outputs": [
      {
        "internalType": "address",
        "name": "",
        "type": "address"
      }
    ],
    "stateMutability": "view",
    "type": "function"
  },
  {
    "inputs": [],
    "name": "paySubscription",
    "outputs": [],
    "stateMutability": "payable",
    "type": "function"
  },
  {
    "inputs": [],
    "name": "paymentDueTime",
    "outputs": [
      {
        "internalType": "uint256",
        "name": "",
        "type": "uint256"
      }
    ],
    "stateMutability": "view",
    "type": "function"
  },
  {
    "inputs": [],
    "name": "platformFeeRate",
    "outputs": [
      {
        "internalType": "uint256",
        "name": "",
        "type": "uint256"
      }
    ],
    "stateMutability": "view",
    "type": "function"
  },
  {
    "inputs": [],
    "name": "proposalCounter",
    "outputs": [
      {
        "internalType": "uint256",
        "name": "",
        "type": "uint256"
      }
    ],
    "stateMutability": "view",
    "type": "function"
  },
  {
    "inputs": [
      {
        "internalType": "uint256",
        "name": "",
        "type": "uint256"
      }
    ],
    "name": "proposals",
    "outputs": [
      {
        "internalType": "uint256",
        "name": "id",
        "type": "uint256"
      },
      {
        "internalType": "string",
        "name": "description",
        "type": "string"
      },
      {
        "internalType": "uint256",
        "name": "forVotes",
        "type": "uint256"
      },
      {
        "internalType": "uint256",
        "name": "againstVotes",
        "type": "uint256"
      },
      {
        "internalType": "uint256",
        "name": "startTime",
        "type": "uint256"
      },
      {
        "internalType": "uint256",
        "name": "endTime",
        "type": "uint256"
      },
      {
        "internalType": "bool",
        "name": "executed",
        "type": "bool"
      },
      {
        "internalType": "bool",
        "name": "canceled",
        "type": "bool"
      }
    ],
    "stateMutability": "view",
    "type": "function"
  },
  {
    "inputs": [
      {
        "internalType": "uint256",
        "name": "quarter",
        "type": "uint256"
      },
      {
        "internalType": "uint256",
        "name": "totalAmount",
        "type": "uint256"
      }
    ],
    "name": "registerDividend",
    "outputs": [],
    "stateMutability": "payable",
    "type": "function"
  },
  {
    "inputs": [],
    "name": "renounceOwnership",
    "outputs": [],
    "stateMutability": "nonpayable",
    "type": "function"
  },
  {
    "inputs": [
      {
        "internalType": "address",
        "name": "_newOperator",
        "type": "address"
      }
    ],
    "name": "setEmergencyOperator",
    "outputs": [],
    "stateMutability": "nonpayable",
    "type": "function"
  },
  {
    "inputs": [
      {
        "internalType": "uint256",
        "name": "_platformFeeRate",
        "type": "uint256"
      },
      {
        "internalType": "uint256",
        "name": "_daoFeeRate",
        "type": "uint256"
      }
    ],
    "name": "setFeeRates",
    "outputs": [],
    "stateMutability": "nonpayable",
    "type": "function"
  },
  {
    "inputs": [
      {
        "internalType": "uint256",
        "name": "amount",
        "type": "uint256"
      }
    ],
    "name": "subscribe",
    "outputs": [],
    "stateMutability": "nonpayable",
    "type": "function"
  },
  {
    "inputs": [],
    "name": "subscriptionEndTime",
    "outputs": [
      {
        "internalType": "uint256",
        "name": "",
        "type": "uint256"
      }
    ],
    "stateMutability": "view",
    "type": "function"
  },
  {
    "inputs": [],
    "name": "subscriptionStartTime",
    "outputs": [
      {
        "internalType": "uint256",
        "name": "",
        "type": "uint256"
      }
    ],
    "stateMutability": "view",
    "type": "function"
  },
  {
    "inputs": [],
    "name": "totalCollectedFees",
    "outputs": [
      {
        "internalType": "uint256",
        "name": "",
        "type": "uint256"
      }
    ],
    "stateMutability": "view",
    "type": "function"
  },
  {
    "inputs": [
      {
        "internalType": "address",
        "name": "newOwner",
        "type": "address"
      }
    ],
    "name": "transferOwnership",
    "outputs": [],
    "stateMutability": "nonpayable",
    "type": "function"
  },
  {
    "inputs": [
      {
        "internalType": "uint256",
        "name": "proposalId",
        "type": "uint256"
      },
      {
        "internalType": "bool",
        "name": "support",
        "type": "bool"
      }
    ],
    "name": "vote",
    "outputs": [],
    "stateMutability": "nonpayable",
    "type": "function"
  },
  {
    "inputs": [],
    "name": "withdrawFees",
    "outputs": [],
    "stateMutability": "nonpayable",
    "type": "function"
  },
  {
    "stateMutability": "payable",
    "type": "receive"
  }
]